liftover_bam/__init__.py
liftover_bam-0.1.0.dist-info/WHEEL
liftover_bam-0.1.0.dist-info/METADATA
liftover_bam-0.1.0.dist-info/RECORD
