Metadata-Version: 2.1
Name: liftover-bam
Version: 0.1.0
Summary: A simple module to liftover bam alignments
License: MIT
Author: Douglas Wu
Author-email: wckdouglas@gmail.com
Requires-Python: >=3.9,<4.0
Classifier: License :: OSI Approved :: MIT License
Classifier: Programming Language :: Python :: 3
Classifier: Programming Language :: Python :: 3.10
Classifier: Programming Language :: Python :: 3.9
Provides-Extra: testing
Requires-Dist: pydantic (>=1.8.2,<2.0.0)
Requires-Dist: pysam (==0.18.0)
